schoolmospy/__init__.py
schoolmospy/__main__.py
schoolmospy/core/basic_client.py
schoolmospy/core/events_client.py
schoolmospy/core/homeworks_client.py
schoolmospy/core/marks_client.py
schoolmospy/core/student_client.py
schoolmospy/models/events.py
schoolmospy/models/homeworks.py
schoolmospy/models/marks.py
schoolmospy/models/profile.py
schoolmospy/models/userinfo.py
schoolmospy/utils/exceptions.py
schoolmospy/utils/logging.py
schoolmospy-0.2.1.dist-info/METADATA
schoolmospy-0.2.1.dist-info/WHEEL
schoolmospy-0.2.1.dist-info/licenses/LICENSE
schoolmospy-0.2.1.dist-info/RECORD
