Metadata-Version: 2.4
Name: schoolmospy
Version: 0.2.1
Summary: A lightweight async Python wrapper for school.mos.ru APIs
License: GPL-3.0-only
License-File: LICENSE
Keywords: school,mos,api,education,async,wrapper,python
Author: Ivan Kriventsev
Author-email: xd2dd@icloud.com
Requires-Python: >=3.12
Classifier: Programming Language :: Python :: 3.12
Classifier: License :: OSI Approved :: GNU General Public License v3 (GPLv3)
Classifier: Operating System :: OS Independent
Classifier: Intended Audience :: Developers
Classifier: Topic :: Software Development :: Libraries :: Python Modules
Requires-Dist: aiohttp (>=3.12.15,<4.0.0)
Requires-Dist: httpx (>=0.28.1,<0.29.0)
Requires-Dist: pydantic (>=2.11.9,<3.0.0)
Project-URL: Documentation, https://xd2dd.github.io/schoolmospy
Project-URL: Homepage, https://github.com/xd2dd/schoolmospy
Project-URL: Issues, https://github.com/xd2dd/schoolmospy/issues
